README
setup.py
shaw/__init__.py
shaw/concurrence.py
shaw/const.py
shaw/decorator.py
shaw/errors.py
shaw/example.py
shaw/exception.py
shaw/func.py
shaw/log.py
shaw/schema.py
shaw.egg-info/PKG-INFO
shaw.egg-info/SOURCES.txt
shaw.egg-info/dependency_links.txt
shaw.egg-info/requires.txt
shaw.egg-info/top_level.txt
shaw/types/__init__.py
shaw/types/d.py
shaw/types/l.py
shaw/web/__init__.py
shaw/web/parser.py
shaw/web/request.py
shaw/web/web.py