Metadata-Version: 1.1
Name: shaw
Version: 1.0.1
Summary: Common python package
Home-page: https://github.com/hangyan/shaw
Author: Hang Yan
Author-email: yanhangyhy@gmail.com
License: GPL V3
Keywords: common utils web
Platform: UNKNOWN
Classifier: Development Status :: 5 - Production/Stable
Classifier: Programming Language :: Python :: 2
Classifier: Programming Language :: Python :: 2.6
Classifier: Programming Language :: Python :: 2.7
